build/lib/build/lib/unused_deps/__init__.py
build/lib/build/lib/unused_deps/__main__.py
build/lib/build/lib/unused_deps/compat.py
build/lib/build/lib/unused_deps/config.py
build/lib/build/lib/unused_deps/dist_info.py
build/lib/build/lib/unused_deps/errors.py
build/lib/build/lib/unused_deps/files.py
build/lib/build/lib/unused_deps/import_finder.py
build/lib/build/lib/unused_deps/main.py
build/lib/build/lib/unused_deps/py.typed
build/lib/unused_deps/__init__.py
build/lib/unused_deps/__main__.py
build/lib/unused_deps/compat.py
build/lib/unused_deps/config.py
build/lib/unused_deps/dist_info.py
build/lib/unused_deps/errors.py
build/lib/unused_deps/files.py
build/lib/unused_deps/import_finder.py
build/lib/unused_deps/main.py
build/lib/unused_deps/py.typed
unused_deps/__init__.py
unused_deps/__main__.py
unused_deps/compat.py
unused_deps/config.py
unused_deps/dist_info.py
unused_deps/errors.py
unused_deps/files.py
unused_deps/import_finder.py
unused_deps/main.py
unused_deps/py.typed
py_unused_deps-0.4.2.dist-info/LICENSE
py_unused_deps-0.4.2.dist-info/METADATA
py_unused_deps-0.4.2.dist-info/WHEEL
py_unused_deps-0.4.2.dist-info/entry_points.txt
py_unused_deps-0.4.2.dist-info/top_level.txt
py_unused_deps-0.4.2.dist-info/RECORD
