Metadata-Version: 2.1
Name: py-unused-deps
Version: 0.4.2
Summary: Find unused dependencies in your python project
Author-email: Matthew Hughes <matthewhughes934@gmail.com>
Project-URL: homepage, https://github.com/matthewhughes934/py-unused-deps
Classifier: Programming Language :: Python :: 3
Classifier: Programming Language :: Python :: 3.8
Classifier: Programming Language :: Python :: 3.9
Classifier: Programming Language :: Python :: 3.10
Classifier: Programming Language :: Python :: 3.11
Classifier: Programming Language :: Python :: 3.12
Classifier: License :: OSI Approved :: GNU General Public License v2 (GPLv2)
Classifier: Operating System :: OS Independent
Requires-Python: >=3.8
License-File: LICENSE
Requires-Dist: tomli; python_version <= "3.11"
Requires-Dist: packaging
